khoros/__init__.py
khoros/auth.py
khoros/core.py
khoros/liql.py
khoros/errors/__init__.py
khoros/errors/exceptions.py
khoros/errors/handlers.py
khoros/utils/__init__.py
khoros/utils/core_utils.py
khoros/utils/helper.py
khoros/utils/version.py
khoros/utils/tests/__init__.py
khoros/utils/tests/test_library_import.py
khoros/utils/tests/test_liql_where_parsing.py
khoros-1.0.0.dist-info/LICENSE
khoros-1.0.0.dist-info/METADATA
khoros-1.0.0.dist-info/WHEEL
khoros-1.0.0.dist-info/top_level.txt
khoros-1.0.0.dist-info/RECORD
