Metadata-Version: 2.1
Name: khoros
Version: 1.0.0
Summary: Useful tools and utilities to assist in managing a Khoros Community (formerly Lithium) environment.
Home-page: https://github.com/jeffshurtliff/khoros
Author: Jeff Shurtliff
Author-email: jeff.shurtliff@rsa.com
License: UNKNOWN
Platform: UNKNOWN
Classifier: Development Status :: 1 - Planning
Classifier: Environment :: Web Environment
Classifier: Intended Audience :: Information Technology
Classifier: Intended Audience :: System Administrators
Classifier: License :: OSI Approved :: MIT License
Classifier: Natural Language :: English
Classifier: Operating System :: OS Independent
Classifier: Programming Language :: Python :: 3.6
Classifier: Programming Language :: Python :: 3.7
Classifier: Programming Language :: Python :: 3.8
Classifier: Topic :: Communications
Classifier: Topic :: Internet :: WWW/HTTP :: Dynamic Content :: Content Management System
Classifier: Topic :: Internet :: WWW/HTTP :: Dynamic Content :: Message Boards
Classifier: Topic :: Internet :: WWW/HTTP :: Site Management
Requires-Python: >=3.6, <3.8.1
